README.md
setup.py
bin/dvg-utils
dvg_utils.egg-info/PKG-INFO
dvg_utils.egg-info/SOURCES.txt
dvg_utils.egg-info/dependency_links.txt
dvg_utils.egg-info/top_level.txt
dvgutils/__init__.py
dvgutils/colors.py
dvgutils/config.py
dvgutils/fs.py
dvgutils/logger.py
dvgutils/misc.py
dvgutils/vis.py
dvgutils/commands/__init__.py
dvgutils/commands/images_to_video.py
dvgutils/commands/plot_metrics.py
dvgutils/commands/video_to_images.py
dvgutils/helpers/__init__.py
dvgutils/helpers/observable.py
dvgutils/helpers/timeit.py
dvgutils/modules/__init__.py
dvgutils/modules/image_capture.py
dvgutils/modules/metrics.py
dvgutils/modules/progress.py
dvgutils/modules/save_image.py
dvgutils/modules/save_video.py
dvgutils/modules/show_image.py
dvgutils/modules/transform.py
dvgutils/modules/video_capture/__init__.py
dvgutils/modules/video_capture/camera_video_capture.py
dvgutils/modules/video_capture/file_video_capture.py
dvgutils/modules/video_capture/pi_camera_video_capture.py
dvgutils/modules/video_capture/stream_video_capture.py
dvgutils/modules/video_capture/video_capture.py
dvgutils/pipeline/__init__.py
dvgutils/pipeline/capture_image_pipe.py
dvgutils/pipeline/capture_video_pipe.py
dvgutils/pipeline/metrics_pipe.py
dvgutils/pipeline/observable.py
dvgutils/pipeline/pipeline.py
dvgutils/pipeline/progress_pipe.py
dvgutils/pipeline/save_image_pipe.py
dvgutils/pipeline/save_video_pipe.py
dvgutils/pipeline/show_image_pipe.py