Metadata-Version: 2.1
Name: dvg-utils
Version: 0.1.2
Summary: DeepVisionGuru utilities for image/video capturing and processing
Home-page: https://github.com/jagin/dvg-utils
Author: Jarosław Gilewski
Author-email: jgilewski@jagin.pl
License: MIT
Keywords: computer vision,image processing,opencv
Platform: UNKNOWN
Classifier: Programming Language :: Python :: 3
Classifier: Programming Language :: Python :: 3.6
Classifier: Programming Language :: Python :: 3.7
Classifier: Programming Language :: Python :: 3.8
Classifier: Environment :: Console
Classifier: Intended Audience :: Developers
Classifier: License :: OSI Approved :: MIT License
Classifier: Operating System :: OS Independent
Requires-Python: >=3.6
